{
	"info": {
		"_postman_id": "da22291d-290b-4f43-86de-c21dab12d6bd",
		"name": "Blog-API",
		"schema": "https://schema.getpostman.com/json/collection/v2.0.0/collection.json"
	},
	"item": [
		{
			"name": "todos",
			"item": [
				{
					"name": "All todos",
					"id": "1e5ffdff-1843-4d8d-9c48-16aed3626f2c",
					"protocolProfileBehavior": {
						"disableBodyPruning": true
					},
					"request": {
						"method": "GET",
						"header": [],
						"url": "{{base_url}}/todos",
						"description": "Retrieves all todos from the API.\n\n**Method & Path:** `GET {{base_url}}/todos`\n\nThis endpoint returns a complete list of todo objects. The `{{base_url}}` environment variable must be set in the active environment (e.g., `https://dummyjson.com`).\n\n**Response**\n\nReturns a JSON object containing a `todos` array. Each todo object includes the following fields:\n\n| Field | Type | Description |\n|-------|------|-------------|\n| `id` | integer | Unique identifier of the todo |\n| `todo` | string | The todo task description |\n| `completed` | boolean | Whether the todo has been completed |\n| `userId` | integer | ID of the user the todo belongs to |\n\n**Example Response:**\n```json\n{\n  \"todos\": [\n    { \"id\": 1, \"todo\": \"Do something nice for someone you care about\", \"completed\": false, \"userId\": 152 },\n    { \"id\": 2, \"todo\": \"Memorize a poem\", \"completed\": true, \"userId\": 13 }\n  ]\n}\n```"
					},
					"response": []
				},
				{
					"name": "todos By ID",
					"id": "d68ac538-f378-4bf2-9bee-a9cf7c37b2d1",
					"protocolProfileBehavior": {
						"disableBodyPruning": true
					},
					"request": {
						"method": "GET",
						"header": [],
						"url": "{{base_url}}/todos/{{user_id}}"
					},
					"response": []
				},
				{
					"name": "Create todos by ID",
					"id": "8104f200-024e-43ba-8fb0-aa1ca54d6a56",
					"protocolProfileBehavior": {
						"disableBodyPruning": true
					},
					"request": {
						"method": "POST",
						"header": [],
						"body": {
							"mode": "raw",
							"raw": "{\r\n        \"userId\": 5,\r\n        \"id\": 201,\r\n        \"title{{todo_title}}\": \"Formation Postman\",\r\n        \"completed\": false\r\n    }",
							"options": {
								"raw": {
									"language": "json"
								}
							}
						},
						"url": "{{base_url}}/todos/{{post_path}}"
					},
					"response": []
				},
				{
					"name": "Complete todos Modification by ID",
					"id": "4b9cc1d4-5f36-41b7-9e5b-50775a0e32f0",
					"protocolProfileBehavior": {
						"disableBodyPruning": true
					},
					"request": {
						"method": "PUT",
						"header": [],
						"body": {
							"mode": "raw",
							"raw": "{\r\n    \"userId\": 56,\r\n    \"title\": \"Formation Postam Jour 2 Postman\",\r\n    \"completed\": true\r\n}",
							"options": {
								"raw": {
									"language": "json"
								}
							}
						},
						"url": "{{base_url}}/todos/{{todo_id}}"
					},
					"response": []
				},
				{
					"name": "Partial todos Modification by ID",
					"id": "034c150d-fc08-4d58-aa1b-55c1989b1538",
					"protocolProfileBehavior": {
						"disableBodyPruning": true
					},
					"request": {
						"method": "PATCH",
						"header": [],
						"body": {
							"mode": "raw",
							"raw": "{\r\n    \"userId\": 56,\r\n    \"title\": \"Formation Postam Jour 2 PostmanPostman finished\",\r\n    \"completed\": true\r\n}",
							"options": {
								"raw": {
									"language": "json"
								}
							}
						},
						"url": "{{base_url}}/todos/{{todo_id}}"
					},
					"response": []
				},
				{
					"name": "Delete todos by ID",
					"id": "79b1bbf1-d9b5-478c-a8e9-83b6a5d96fb0",
					"protocolProfileBehavior": {
						"disableBodyPruning": true
					},
					"request": {
						"method": "DELETE",
						"header": [],
						"body": {
							"mode": "raw",
							"raw": "{\r\n    \"userId\": 56,\r\n    \"title\": \"Formation Postam Jour 2 PostmanPostman finished\",\r\n    \"completed\": true\r\n}"
						},
						"url": "{{base_url}}/todos/{{todo_id}}"
					},
					"response": []
				}
			],
			"id": "d2bd159f-b479-4dcc-953a-6911d30db5c6"
		},
		{
			"name": "Users",
			"item": [],
			"id": "f4e83c44-123d-46b6-ab7d-3fe006c42920"
		},
		{
			"name": "Auth",
			"item": [
				{
					"name": "Dummy Jason Token",
					"event": [
						{
							"listen": "test",
							"script": {
								"id": "9748f36d-f464-42a6-883f-5103cf60eb38",
								"exec": [
									"const responseJson = pm.response.json();\r",
									"pm.environment.set(\"jason_token\",responseJson.accessToken);\r",
									"\r",
									""
								],
								"type": "text/javascript",
								"packages": {},
								"requests": {}
							}
						}
					],
					"id": "8113131f-4a0f-4b83-a841-dd0507242974",
					"protocolProfileBehavior": {
						"disableBodyPruning": true
					},
					"request": {
						"method": "POST",
						"header": [],
						"body": {
							"mode": "raw",
							"raw": "{\r\n    \"username\": \"alexanderj\",\r\n    \"password\": \"alexanderjpass\"\r\n}",
							"options": {
								"raw": {
									"language": "json"
								}
							}
						},
						"url": "{{base_url}}/auth/login"
					},
					"response": []
				},
				{
					"name": "get auth me",
					"id": "f7d465ad-65ae-49ca-bad0-758e4f2b0d8f",
					"protocolProfileBehavior": {
						"disableBodyPruning": true
					},
					"request": {
						"method": "GET",
						"header": [],
						"url": "{{base_url}}/auth/me"
					},
					"response": []
				}
			],
			"id": "14cb9b87-8ec5-432e-85ac-c09a45c640e5"
		},
		{
			"name": "Posts",
			"item": [
				{
					"name": "All Posts",
					"id": "237408b2-4203-40f9-af71-60a6d8e5c549",
					"protocolProfileBehavior": {
						"disableBodyPruning": true
					},
					"request": {
						"method": "GET",
						"header": [],
						"url": {
							"raw": "{{base_url}}/posts",
							"host": [
								"{{base_url}}"
							],
							"path": [
								"posts"
							],
							"query": [
								{
									"key": "_limit",
									"value": "{{_limit}}"
								},
								{
									"key": "_start",
									"value": "60"
								}
							]
						},
						"description": "Retrieves a list of all posts.\n\n**Method:** GET  \n**Endpoint:** `{{base_url}}/posts`\n\n**Response:**\n- **200 OK** – Returns a JSON object containing an array of post objects. Each post includes:\n  - `id` – Unique identifier of the post\n  - `title` – Title of the post\n  - `body` – Full text content of the post\n  - `tags` – Array of tags associated with the post\n  - `reactions` – Object containing `likes` and `dislikes` counts\n  - `views` – Number of views\n  - `userId` – ID of the user who created the post\n\n**Notes:**\n- Uses the `{{base_url}}` environment variable as the base URL.\n- No authentication or query parameters are required."
					},
					"response": []
				},
				{
					"name": "Posts by ID",
					"id": "dd681d64-1f81-44c1-8b1a-1df57a71c3ee",
					"protocolProfileBehavior": {
						"disableBodyPruning": true
					},
					"request": {
						"method": "GET",
						"header": [],
						"url": "{{base_url}}/posts/{{post_id}}"
					},
					"response": []
				},
				{
					"name": "Comments by Post ID",
					"id": "92e666bd-c8cd-4323-9088-8987f4cd96bf",
					"protocolProfileBehavior": {
						"disableBodyPruning": true
					},
					"request": {
						"method": "GET",
						"header": [],
						"url": "{{base_url}}/posts/{{post_id}}/comments"
					},
					"response": []
				},
				{
					"name": "Create Post",
					"id": "f9712b29-e805-4a38-97be-5713e7cd38c4",
					"protocolProfileBehavior": {
						"disableBodyPruning": true
					},
					"request": {
						"method": "POST",
						"header": [],
						"body": {
							"mode": "raw",
							"raw": "{\"userId\": 5,\r\n\"title\": \"test Post Postman formation Nabil\",\r\n\"body\": \"Nabil test post formation Postman .\"\r\n}",
							"options": {
								"raw": {
									"language": "json"
								}
							}
						},
						"url": "{{base_url}}/posts{{post_path}}"
					},
					"response": []
				},
				{
					"name": "Delete Post",
					"id": "f9dc3171-9101-4bb7-8b39-d015e0a916a5",
					"protocolProfileBehavior": {
						"disableBodyPruning": true
					},
					"request": {
						"method": "DELETE",
						"header": [],
						"url": "{{base_url}}/posts/{{post_id}}"
					},
					"response": []
				},
				{
					"name": "Modify Post",
					"id": "7f93a37b-3de7-475e-ad87-f9d9890cbfdb",
					"protocolProfileBehavior": {
						"disableBodyPruning": true
					},
					"request": {
						"method": "PUT",
						"header": [],
						"body": {
							"mode": "raw",
							"raw": "{\r\n    \"id\": 1,\r\n    \"title\": \"His fatther had always taught him\",\r\n    \"body\": \"His father had always taught him not to ever think of himself as better than others. He'd tried to live by this motto. He never looked down on those who were less fortunate or who had less money than him. But the stupidity of the group of people he was talking to made him change his mind.\",\r\n    \"tags\": [\r\n        \"history\",\r\n        \"american\",\r\n        \"crime\",\r\n        \"fiction\"\r\n    ],\r\n    \"reactions\": {\r\n        \"likes\": 192,\r\n        \"dislikes\": 25\r\n    },\r\n    \"views\": 305,\r\n    \"userId\": 121\r\n}",
							"options": {
								"raw": {
									"language": "json"
								}
							}
						},
						"url": "{{base_url}}/posts/{{post_id}}"
					},
					"response": []
				},
				{
					"name": "Partially Modify Post",
					"id": "fbaa232f-01be-4910-8381-55a449468702",
					"protocolProfileBehavior": {
						"disableBodyPruning": true
					},
					"request": {
						"method": "PATCH",
						"header": [],
						"body": {
							"mode": "raw",
							"raw": "{\r\n    \"id\": 1,\r\n    \"title\": \"His fatther and mother  had always taught him\",\r\n    \"body\": \"His father and mother  had always taught him not to ever think of himself as better than others. He'd tried to live by this motto. He never looked down on those who were less fortunate or who had less money than him. But the stupidity of the group of people he was talking to made him change his mind.\",\r\n    \"tags\": [\r\n        \"history\",\r\n        \"american\",\r\n        \"crime\"\r\n        \r\n    ],\r\n    \"reactions\": {\r\n        \"likes\": 192,\r\n        \"dislikes\": 25\r\n    },\r\n    \"views\": 3005,\r\n    \"userId\": 111\r\n}\r\n",
							"options": {
								"raw": {
									"language": "json"
								}
							}
						},
						"url": "{{base_url}}/posts/{{post_id}}"
					},
					"response": []
				}
			],
			"id": "dae801ce-b2a8-4ff0-9adf-c38ff18add85"
		}
	],
	"auth": {
		"type": "bearer",
		"bearer": {
			"token": "{{jason_token}}"
		}
	},
	"event": [
		{
			"listen": "prerequest",
			"script": {
				"id": "4d8466c1-4a1c-4b72-95ed-52ae92cbb72e",
				"type": "text/javascript",
				"packages": {},
				"requests": {},
				"exec": [
					""
				]
			}
		},
		{
			"listen": "test",
			"script": {
				"id": "aaf74c33-585b-4e3f-b6cf-9c79d7e7735d",
				"type": "text/javascript",
				"packages": {},
				"requests": {},
				"exec": [
					""
				]
			}
		}
	]
}